{
  "updated": "2026-07-14 00:03",
  "mid": 17.412,
  "providers": [
    {
      "name": "GME Remit",
      "vndPerKrw": 17.412,
      "fee": 5000
    },
    {
      "name": "Hanpass",
      "vndPerKrw": 17.3423,
      "fee": 4000
    },
    {
      "name": "E9pay",
      "vndPerKrw": 17.2727,
      "fee": 3000
    },
    {
      "name": "Sentbe",
      "vndPerKrw": 17.203,
      "fee": 0
    }
  ],
  "history": [
    17.3601,
    17.3601,
    17.3601,
    17.3601,
    17.3601,
    17.3601,
    17.3601,
    17.3601,
    17.412,
    17.412,
    17.412,
    17.412
  ]
}